typing_utils/__init__.py
typing_utils-0.1.0.dist-info/LICENSE
typing_utils-0.1.0.dist-info/METADATA
typing_utils-0.1.0.dist-info/WHEEL
typing_utils-0.1.0.dist-info/top_level.txt
typing_utils-0.1.0.dist-info/RECORD
